grokipedia/__init__.py
grokipedia/cli.py
grokipedia/client.py
grokipedia/exceptions.py
grokipedia/http.py
grokipedia/models.py
grokipedia/parser.py
grokipedia/py.typed
grokipedia/robots.py
grokipedia/sitemap.py
grokipedia_sdk-0.2.0.dist-info/licenses/LICENSE
grokipedia_sdk-0.2.0.dist-info/METADATA
grokipedia_sdk-0.2.0.dist-info/WHEEL
grokipedia_sdk-0.2.0.dist-info/entry_points.txt
grokipedia_sdk-0.2.0.dist-info/top_level.txt
grokipedia_sdk-0.2.0.dist-info/RECORD
